eg/spreader/__init__.py
eg/spreader/_spreader.cp38-win_amd64.pyd
eg/spreader/sheet.py
eg/spreader/types.py
eg.spreader-0.1.0.dist-info/LICENSE
eg.spreader-0.1.0.dist-info/METADATA
eg.spreader-0.1.0.dist-info/WHEEL
eg.spreader-0.1.0.dist-info/top_level.txt
eg.spreader-0.1.0.dist-info/RECORD
