Metadata-Version: 2.1
Name: eg.spreader
Version: 0.1.0
Summary: Fast spreadsheet logic library
Home-page: https://github.com/gershnik/spreader.py
Author: Eugene Gershnik
Author-email: gershnik@hotmail.com
License: BSD-3-Clause
Download-URL: http://pypi.python.org/pypi/spreader/
Platform: UNKNOWN
Requires-Python: >=3.7
License-File: LICENSE
